msdb/__init__.py
msdb/admin.py
msdb/apps.py
msdb/tests.py
msdb/views.py
msdb/migrations/__init__.py
msdb/models/__init__.py
msdb/models/admonition.py
msdb/models/admonition_action.py
msdb/models/admonition_template.py
msdb/models/alert.py
msdb/models/base_model.py
msdb/models/book.py
msdb/models/bookpart.py
msdb/models/comment.py
msdb/models/contest.py
msdb/models/correction_request.py
msdb/models/correction_request_action.py
msdb/models/license.py
msdb/models/like.py
msdb/models/member.py
msdb/models/message.py
msdb/models/post.py
msdb/models/rating.py
msdb/models/section.py
msdb/models/site_param.py
msdb/models/tag.py
msdb/validators/__init__.py
msdb/validators/not_passed.py
msdb/validators/required_age.py
muses_msdb-0.1.1600998865.dist-info/METADATA
muses_msdb-0.1.1600998865.dist-info/WHEEL
muses_msdb-0.1.1600998865.dist-info/top_level.txt
muses_msdb-0.1.1600998865.dist-info/RECORD
